{
  "_id": "ff403d1a85a90f10",
  "name": "Book, Prayer",
  "type": "equipment",
  "img": "icons/svg/item-bag.svg",
  "system": {
    "description": {
      "value": "<p>A religious text containing prayers, hymns, and devotional writings dedicated to a specific deity or faith.</p>"
    },
    "equipmentType": "adventuring-gear",
    "weight": 2.0,
    "cost": 5.0,
    "quantity": 1,
    "equipped": false,
    "capacity": "",
    "brightLight": 0,
    "dimLight": 0,
    "duration": "",
    "uses": {
      "value": 0,
      "max": 0
    },
    "consumable": false,
    "associatedSkill": "",
    "toolBonus": 0,
    "rarity": "",
    "requiresAttunement": false,
    "magicalProperties": "",
    "properties": "",
    "notes": ""
  },
  "effects": [],
  "_key": "!items!ff403d1a85a90f10"
}