{
  "_id": "f9ceecce3c864e9b",
  "name": "Clothes, Traveler's",
  "type": "equipment",
  "img": "icons/svg/item-bag.svg",
  "system": {
    "description": {
      "value": "<p>Durable clothing designed for long journeys, featuring reinforced seams and practical pockets. Includes multiple layers for varying weather.</p>"
    },
    "equipmentType": "adventuring-gear",
    "weight": 4.0,
    "cost": 15.0,
    "quantity": 1,
    "equipped": false,
    "properties": "",
    "notes": ""
  },
  "effects": [],
  "_key": "!items!f9ceecce3c864e9b"
}