{
  "_id": "ba384489c661e282",
  "name": "Spear",
  "type": "weapon",
  "img": "icons/weapons/swords/sword-long-crossguard-brown.webp",
  "system": {
    "description": {
      "value": "<p>A pointed blade or head mounted on a long shaft, creating humanity's oldest and most ubiquitous weapon. The spear offers reach, throwing capability, and the shaft can deliver bludgeoning strikes. This category includes javelins (lighter throwing spears), lances (cavalry-focused), pilums, assegai, and similar hafted piercing weapons. Universal across cultures, the spear's simplicity belies its effectiveness.</p>"
    },
    "damage": {
      "base": 6,
      "type": "piercing",
      "alternate": 4,
      "alternateType": "bludgeoning",
      "multiType": ""
    },
    "range": {
      "normal": 30,
      "medium": 60,
      "long": 120
    },
    "attackModes": [
      {
        "name": "Melee",
        "type": "melee",
        "skill": "melee",
        "damageAttr": "strength",
        "defenseType": "melee",
        "damage": {
          "base": 6,
          "alternate": 0
        },
        "range": {
          "normal": 0,
          "medium": 0,
          "long": 0
        }
      },
      {
        "name": "Thrown",
        "type": "thrown",
        "skill": "ranged",
        "damageAttr": "dexterity",
        "defenseType": "ranged",
        "damage": {
          "base": 6,
          "alternate": 0
        },
        "range": {
          "normal": 30,
          "medium": 60,
          "long": 120
        }
      }
    ],
    "weight": 5.0,
    "cost": 12.0,
    "quantity": 1,
    "properties": [
      "versatile",
      "alternate-strike",
      "thrown",
      "reach"
    ],
    "reload": "",
    "requirements": "",
    "notes": ""
  },
  "effects": [],
  "_key": "!items!ba384489c661e282"
}