{
  "name": "Mounted Combatant",
  "type": "feat",
  "img": "icons/svg/d20.svg",
  "system": {
    "tier": 1,
    "prerequisites": [],
    "benefit": {
      "text": "**Tier:** 2\n**Prerequisites:** Riding 4\n**Benefit:** Attacks against your mount add 1 to both dice. If mount is hit, you can redirect attack to yourself instead. While mounted, melee attacks against creatures smaller than your mount subtract 1 from both dice\n**Usage:** Passive\n**Keyword:** [Combat], [Mounted]"
    },
    "usage": "",
    "keywords": [],
    "effects": []
  },
  "flags": {}
}