{
  "_id": "06495efed232a2ba",
  "name": "Ritual Efficiency",
  "type": "feat",
  "img": "icons/magic/symbols/star-rising-purple.webp",
  "system": {
    "description": {
      "value": "<p>You've streamlined the process without cutting corners, halving the time and finding ways around missing pieces.</p>"
    },
    "flavorText": "",
    "xpCost": 40,
    "classification": "standard",
    "prerequisites": {
      "attributes": {},
      "skills": "arcane:4",
      "feats": [],
      "tier": 0,
      "other": "any magical tradition trait with ritual casting"
    },
    "benefits": "<p>Cast rituals in half the normal time (5 minutes instead of 10). Component costs reduced by 25%. When missing a component, can make [[/check skill=arcane]] (Hard task) to substitute similar materials. Can teach rituals to other casters (they learn in half time if you teach them)</p>",
    "usageType": "passive",
    "usage": {
      "mode": "passive",
      "uses": null,
      "recharge": null,
      "text": "Passive"
    },
    "keywords": "[Magic]",
    "notes": "",
    "effects": []
  },
  "effects": [],
  "_key": "!items!06495efed232a2ba"
}