{
  "_id": "b09d023ff87e4b4e",
  "name": "Use Special Ability",
  "type": "action",
  "img": "icons/skills/trades/construction-gloves-yellow.webp",
  "system": {
    "description": {
      "value": "<ul>\n<li><strong>Cost:</strong> 1 (or as specified by ability)</li>\n<li><strong>Effect:</strong> Use a class feature, feat, or special ability that doesn't fit other categories</li>\n<li><strong>Notes:</strong>\n<ul>\n<li>Specific action cost listed in ability description</li>\n<li>Some abilities may be [Free] or [Reaction] instead</li>\n</ul></li>\n</ul>"
    },
    "actionType": "activate",
    "actionCost": "1",
    "trigger": "",
    "effect": "Use a class feature, feat, or special ability that doesn't fit other categories\n- **Notes:**\n  - Specific action cost listed in ability description\n  - Some abilities may be [Free] or [Reaction] instead",
    "keywords": "",
    "range": "",
    "target": "",
    "frequency": "",
    "special": ""
  },
  "effects": [],
  "_key": "!items!b09d023ff87e4b4e"
}