{
  "_id": "1b717e29c9ac4385",
  "name": "Ward",
  "type": "background",
  "img": "icons/svg/book.svg",
  "system": {
    "description": {
      "value": "<p>You were raised in a noble or wealthy household, educated and cared for but never quite family. The experience gave you access to privilege while reminding you constantly that it could be taken away. You learned etiquette, history, and the subtle art of navigating high society from the margins. Now you're free to make your own way, though whether that freedom is liberating or terrifying probably depends on the day. <strong>Skills:</strong> Society 2, History 2, Empathy 1, Perception 1, +40 XP <strong>Equipment:</strong> Fine clothes, general topic book, quill, ink, vellum parchment x2, shoes <strong>Feature</strong> - Noble Education: You were raised in a noble household and understand etiquette and high society, though you lack the full privileges and recognition that true nobles command.</p>"
    },
    "startingXP": 0,
    "skillBonuses": "",
    "startingEquipment": "",
    "suggestedFeats": "",
    "features": "",
    "sampleNames": "",
    "traits": "",
    "notes": ""
  },
  "effects": [],
  "_key": "!items!1b717e29c9ac4385"
}