{
  "_id": "a5ae5f7d",
  "name": "Mageborn (-7)",
  "type": "trait",
  "system": {
    "description": "**Requirements:** Intelligence ≥ 3\n\nYou were born with an innate connection to the planes flowing through your pneuma. Your eyes glow with constant violet light, marking you as a mage from birth. Through careful study and understanding of magical theory, you have learned to channel the eight energies through precise intellectual control.\n\n**Visual Effects:** Your weaves manifest with orbiting glyphs, bright flashes of violet light, and cascading magical symbols. Motes of energy trail from your g",
    "quantity": 1
  },
  "effects": []
}