{
  "_id": "3c6b9b0603ee44de",
  "name": "Calm Emotions",
  "type": "weave",
  "img": "icons/magic/abjuration/abjuration-purple.webp",
  "system": {
    "description": {
      "value": "<p>All creatures in a 20-foot radius sphere at medium range must make Will saves. Compare your weaving successes to each target's save successes. Those you beat can choose to be affected (suppressing Charmed or Frightened) or you can suppress hostility (they become indifferent if not directly threatened). Creatures immune to charm are immune to this weave.</p>"
    },
    "weaveType": "complex",
    "actionCost": 2,
    "energyCost": {
      "primary": {
        "type": "positive",
        "cost": 4
      },
      "supporting": {
        "type": "space",
        "cost": 6
      }
    },
    "range": "Medium, 60 ft. (20-foot radius sphere)",
    "duration": "1 minute",
    "target": "",
    "savingThrow": "will",
    "effect": "",
    "effectType": "",
    "damage": {
      "base": 0,
      "type": "",
      "drInteraction": "",
      "scaling": {}
    },
    "targetingSuccessScaling": "- 0 = Fails\n- 1 = 1 round\n- 2 = 1 minute\n- 3 = 10 minutes",
    "weavingRoll": "Positive Potential + Positive Mastery / Space Potential + Space Mastery",
    "targetingRoll": "Casting Stat + Positive Mastery",
    "appliesEffects": [],
    "deliveryMethod": "save",
    "tags": [
      "aoe",
      "ranged",
      "ritual"
    ]
  },
  "effects": [],
  "_key": "!items!3c6b9b0603ee44de"
}