{
  "_id": "ee87eb4f46fd4054",
  "name": "Counterweave",
  "type": "weave",
  "img": "icons/magic/abjuration/abjuration-purple.webp",
  "system": {
    "description": {
      "value": "<p>Attempt to interrupt a weave being cast. Make an [[/check skill=arcane]] to determine the weave being cast. Must spend Energy equal to or greater than the weave you're countering. Compare your Targeting successes to their weaving successes. If you have more, their weave fails.</p>"
    },
    "weaveType": "simple",
    "actionCost": 1,
    "energyCost": {
      "primary": {
        "type": "space",
        "cost": 4
      },
      "supporting": {
        "type": "",
        "cost": 0
      }
    },
    "range": "Medium, 60 ft.",
    "duration": "Instantaneous",
    "target": "",
    "savingThrow": "none",
    "effect": "Attempt to interrupt a weave being cast. Make an arcana check to determine the weave being cast. Must spend Energy equal to or greater than the weave you're countering. Compare your Targeting successes to their weaving successes. If you have more, their weave fails.",
    "effectType": "control",
    "damage": {
      "base": 0,
      "type": "",
      "drInteraction": "",
      "scaling": {
        "0": {
          "appliesEffects": false,
          "description": "Fails",
          "duration": null
        },
        "1": {
          "appliesEffects": true,
          "description": "Reduce target spell by 1 success",
          "duration": "Reduce target spell by 1 success"
        },
        "2": {
          "appliesEffects": true,
          "description": "Counter successful",
          "duration": "Counter successful"
        },
        "3": {
          "appliesEffects": true,
          "description": "Counter successful + dazed",
          "duration": "Counter successful + dazed"
        }
      }
    },
    "targetingSuccessScaling": "0 = Fails, 1 = Reduce target spell by 1 success, 2 = Counter successful, 3 = Counter successful + dazed",
    "weavingRoll": "Space Potential + Space Mastery",
    "targetingRoll": "Casting Stat + Space Mastery",
    "appliesEffects": [
      {
        "effectId": "dazed",
        "params": {}
      }
    ],
    "deliveryMethod": "automatic",
    "tags": [
      "ranged",
      "utility"
    ]
  },
  "effects": [],
  "_key": "!items!ee87eb4f46fd4054"
}