{
  "_id": "d2f398be9de64e60",
  "name": "Fire Bolt",
  "type": "weave",
  "img": "icons/magic/abjuration/abjuration-purple.webp",
  "system": {
    "description": {
      "value": "<p><strong>Primary Energy:</strong> Fire 2 (bolt of flame, damage) <strong>Supporting Energy:</strong> Space 1 (close range) <strong>Range:</strong> Close, 30 ft. <strong>Duration:</strong> Instantaneous <strong>Total Cost:</strong> 3 Energy <strong>Action:</strong> Complex weave (2 actions) <strong>Weaving Roll:</strong> Fire Potential + Fire Mastery / Space Potential + Space Mastery <strong>Effect:</strong> You hurl a mote of fire at a creature or object within range. Target takes [[/damage 8 type=fire]] damage. This is an attack weave—no saving throw allowed. <strong>Saving Throw:</strong> None (attack weave, weaving successes determine hit quality) <strong>Damage Type:</strong> Fire (energy) <strong>DR Interaction:</strong> Half DR ([[/damage 8 type=fire]] damage vs DR 4 becomes 8 - 2 = [[/damage 6]] damage) <strong>Success Scaling:</strong> 0 = miss, 1 = half damage (4), 2 = full damage (8), 3 = +[[/damage 8]] damage (16 total), 4 = +[[/damage 16]] damage (24 total) <strong>Ignited Condition (at 4 successes):</strong> Target takes [[/damage 1d8 type=fire]] damage at start of each turn. Can use 1 action to make [[/save type=reflex]] (1 success ends) or ally can use 1 action to extinguish.</p>"
    },
    "weaveType": "complex",
    "actionCost": 1,
    "energyCost": {
      "primary": {
        "type": "fire",
        "cost": 2
      },
      "supporting": {
        "type": "space",
        "cost": 1
      }
    },
    "school": "",
    "range": {
      "value": "",
      "distance": 0
    },
    "target": "",
    "areaSize": "",
    "duration": "",
    "durationDetail": "",
    "saveType": "none",
    "saveEffect": "",
    "effectType": "",
    "damage": {
      "base": 0,
      "type": "",
      "drInteraction": "",
      "scaling": ""
    },
    "healing": {
      "base": 0,
      "scaling": ""
    },
    "conditions": "",
    "successEffects": "",
    "specialProperties": "",
    "heightening": ""
  },
  "effects": [],
  "_key": "!items!d2f398be9de64e60"
}