{
  "_id": "3ed18d92d75744d7",
  "name": "Nightmare Manifestation",
  "type": "weave",
  "img": "icons/magic/abjuration/abjuration-purple.webp",
  "system": {
    "description": {
      "value": "<p>Target at medium range makes [[/save type=will]]. Compare your weaving successes to their save successes. If you have more, target sees its worst fear made manifest. Target is Frightened and takes [[/damage 12 type=psychic]] damage at start of each turn. Can repeat [[/save type=will]] each round to end effect (1 success ends effect).</p>"
    },
    "weaveType": "complex",
    "actionCost": 2,
    "energyCost": {
      "primary": {
        "type": "space",
        "cost": 8
      },
      "supporting": {
        "type": "time",
        "cost": 2
      }
    },
    "range": "Medium, 60 ft.",
    "duration": "1 minute",
    "target": "",
    "savingThrow": "will",
    "effect": "",
    "effectType": "",
    "damage": {
      "base": 0,
      "type": "",
      "drInteraction": "ignore",
      "scaling": {}
    },
    "targetingSuccessScaling": "- 0 = fails\n- 1 = Frightened\n- 2 = Frightened (12)\n- 3 = Frightened (16)",
    "weavingRoll": "Space Potential + Space Mastery / Time Potential + Time Mastery",
    "targetingRoll": "Casting Stat + Space Mastery",
    "appliesEffects": [
      {
        "effectId": "frightened",
        "params": {}
      }
    ],
    "deliveryMethod": "save",
    "tags": [
      "control",
      "divination",
      "ranged",
      "ritual"
    ]
  },
  "effects": [],
  "_key": "!items!3ed18d92d75744d7"
}