{
  "_id": "56bd973e389e4b84",
  "name": "Preserve Remains",
  "type": "weave",
  "img": "icons/magic/abjuration/abjuration-purple.webp",
  "system": {
    "description": {
      "value": "<p>Corpse at touch is protected from decay and cannot become undead. Extends time limit for resurrection magic.</p>"
    },
    "weaveType": "complex",
    "actionCost": 2,
    "energyCost": {
      "primary": {
        "type": "positive",
        "cost": 2
      },
      "supporting": {
        "type": "time",
        "cost": 4
      }
    },
    "range": "Touch",
    "duration": "1 hour (or until dispelled)",
    "target": "",
    "savingThrow": "none",
    "effect": "",
    "effectType": "",
    "damage": {
      "base": 0,
      "type": "",
      "drInteraction": "",
      "scaling": {
        "0": {
          "appliesEffects": true,
          "description": "fails",
          "duration": "fails"
        },
        "1": {
          "appliesEffects": true,
          "description": "10 minutes",
          "duration": "10 minutes"
        },
        "2": {
          "appliesEffects": true,
          "description": "1 hour",
          "duration": "1 hour"
        },
        "3": {
          "appliesEffects": true,
          "description": "4 hours",
          "duration": "4 hours"
        },
        "4": {
          "appliesEffects": true,
          "description": "12 hours",
          "duration": "12 hours"
        },
        "5": {
          "appliesEffects": true,
          "description": "1 day",
          "duration": "1 day"
        }
      }
    },
    "successScaling": "",
    "weavingRoll": "",
    "appliesEffects": [],
    "deliveryMethod": "save",
    "tags": [
      "necromantic",
      "touch"
    ]
  },
  "effects": [],
  "_key": "!items!56bd973e389e4b84"
}