{
  "_id": "e3107f3f89484e42",
  "name": "Protection from Energy",
  "type": "weave",
  "img": "icons/magic/abjuration/abjuration-purple.webp",
  "system": {
    "description": {
      "value": "<p>Target at touch gains Resistance (+4 DR) against one chosen damage type (fire, cold, acid, lightning, thunder).</p>"
    },
    "weaveType": "complex",
    "actionCost": 2,
    "energyCost": {
      "primary": {
        "type": "space",
        "cost": 5
      },
      "supporting": {
        "type": "time",
        "cost": 3
      }
    },
    "range": "self, touch",
    "duration": "10 minutes",
    "target": "",
    "savingThrow": "none",
    "effect": "",
    "effectType": "",
    "damage": {
      "base": 0,
      "type": "",
      "drInteraction": "",
      "scaling": {
        "0": {
          "appliesEffects": true,
          "description": "fails",
          "duration": "fails"
        },
        "1": {
          "appliesEffects": true,
          "description": "1 minute",
          "duration": "1 minute"
        },
        "2": {
          "appliesEffects": true,
          "description": "full effect",
          "duration": "full effect"
        },
        "3": {
          "appliesEffects": true,
          "description": "1 hour",
          "duration": "1 hour"
        },
        "4": {
          "appliesEffects": true,
          "description": "1 hour (+8 DR)",
          "duration": "1 hour (+8 DR)"
        },
        "5": {
          "appliesEffects": true,
          "description": "4 hours (+8 DR)",
          "duration": "4 hours (+8 DR)"
        }
      }
    },
    "successScaling": "",
    "weavingRoll": "",
    "appliesEffects": [],
    "deliveryMethod": "save",
    "tags": [
      "buff",
      "defensive",
      "touch"
    ]
  },
  "effects": [],
  "_key": "!items!e3107f3f89484e42"
}