{
  "_id": "7f47bb4a1eee4cfd",
  "name": "Vampiric Touch",
  "type": "weave",
  "img": "icons/magic/abjuration/abjuration-purple.webp",
  "system": {
    "description": {
      "value": "<p>Your touch deals [[/damage 12 type=negative]] damage. You heal HP equal to half damage dealt. Can hold the charge for up to 1 minute and attack multiple times if charge remains. This is an attack weave when discharging—no saving throw on the touch.</p>"
    },
    "weaveType": "complex",
    "actionCost": 2,
    "energyCost": {
      "primary": {
        "type": "negative",
        "cost": 4
      },
      "supporting": {
        "type": "time",
        "cost": 2
      }
    },
    "range": "Touch",
    "duration": "1 minute (charge duration)",
    "target": "",
    "savingThrow": "none",
    "effect": "",
    "effectType": "",
    "damage": {
      "base": 0,
      "type": "",
      "drInteraction": "half",
      "scaling": {
        "0": {
          "appliesEffects": true,
          "description": "fails",
          "duration": "fails"
        },
        "1": {
          "appliesEffects": true,
          "description": "6 damage (heal 3)",
          "duration": "6 damage (heal 3)"
        },
        "2": {
          "appliesEffects": true,
          "description": "12 damage (heal 6)",
          "duration": "12 damage (heal 6)"
        },
        "3": {
          "appliesEffects": true,
          "description": "16 damage (heal 8)",
          "duration": "16 damage (heal 8)"
        },
        "4": {
          "appliesEffects": true,
          "description": "24 damage (heal 12)",
          "duration": "24 damage (heal 12)"
        },
        "5": {
          "appliesEffects": true,
          "description": "24 damage (heal 12) + Applies Effects",
          "duration": "24 damage (heal 12) + Applies Effects"
        }
      }
    },
    "successScaling": "",
    "weavingRoll": "",
    "appliesEffects": [
      {
        "effectId": "weakened",
        "params": {}
      }
    ],
    "deliveryMethod": "save",
    "tags": [
      "healing",
      "touch"
    ]
  },
  "effects": [],
  "_key": "!items!7f47bb4a1eee4cfd"
}