{
  "_id": "671c752c66184840",
  "name": "Curse of Misfortune",
  "type": "trait",
  "img": "icons/skills/social/diplomacy-handshake.webp",
  "system": {
    "description": "- **Action Cost:** 1 [Combat] action\n- **Range:** 60 feet (must see target)\n- **Effect:** Curse one enemy. Make opposed check: your Wisdom + Space Mastery vs their Wisdom + Luck (Will save). If you win (more successes), they have **Misfortune** on their next roll. Rudlu's capricious nature turns against them.\n- **Usage:** Uses 1 Channel Divinity"
  },
  "effects": []
}